mistly/__init__.py
mistly/__main__.py
mistly/genius.py
mistly/song.py
mistly-0.0.6.dist-info/LICENSE
mistly-0.0.6.dist-info/METADATA
mistly-0.0.6.dist-info/WHEEL
mistly-0.0.6.dist-info/entry_points.txt
mistly-0.0.6.dist-info/top_level.txt
mistly-0.0.6.dist-info/RECORD
